Metadata-Version: 2.1
Name: pipfile-freeze
Version: 0.1.4
Summary: A CLI tool to convert Pipfile/Pipfile.lock to requirments.txt
Home-page: https://github.com/mocobk/pipfile-freeze
Author: mocobk
Author-email: mailmzb@163.com
License: MIT
Platform: UNKNOWN
Classifier: Development Status :: 3 - Alpha
Classifier: License :: OSI Approved :: MIT License
Classifier: Programming Language :: Python
Classifier: Programming Language :: Python :: 2
Classifier: Programming Language :: Python :: 2.7
Classifier: Programming Language :: Python :: 3
Classifier: Programming Language :: Python :: 3.4
Classifier: Programming Language :: Python :: 3.5
Classifier: Programming Language :: Python :: 3.6
Classifier: Programming Language :: Python :: 3.7
